<phonenumbers>

	<phonenumber id="1">
		<number>31151231</number>
		<Individuals_id>1</Individuals_id>
	</phonenumber>

	<phonenumber id="2">
		<number>85182931</number>
		<Individuals_id>2</Individuals_id>
	</phonenumber>

	<phonenumber id="3">
		<number>96910236</number>
		<Individuals_id>3</Individuals_id>
	</phonenumber>

	<phonenumber id="4">
		<number>1069122</number>
		<Individuals_id>4</Individuals_id>
	</phonenumber>

	<phonenumber id="5">
		<number>105192</number>
		<Individuals_id>5</Individuals_id>
	</phonenumber>

	<phonenumber id="6">
		<number>68190239</number>
		<Individuals_id>6</Individuals_id>
	</phonenumber>
</phonenumbers>
